{
    "fatness": 0,
    "hairBg": {
        "id": "none"
    },
    "body": {
        "id": "body4",
        "color": "#dcad92"
    },
    "jersey": {
        "id": "jersey3"
    },
    "ear": {
        "id": "ear1",
        "size": 1
    },
    "head": {
        "id": "head1",
        "shave": "rgba(0,0,0,0)"
    },
    "eyeLine": {
        "id": "none"
    },
    "smileLine": {
        "id": "line1",
        "size": 0.68
    },
    "miscLine": {
        "id": "forehead3"
    },
    "facialHair": {
        "id": "none"
    },
    "eye": {
        "id": "eye7",
        "angle": 0
    },
    "eyebrow": {
        "id": "eyebrow13",
        "angle": 5
    },
    "hair": {
        "id": "juice",
        "color": "#302723",
        "flip": false
    },
    "mouth": {
        "id": "smile",
        "flip": false
    },
    "nose": {
        "id": "nose9",
        "flip": false,
        "size": 1.25
    },
    "glasses": {
        "id": "none"
    },
    "accessories": {
        "id": "none"
    }
}