{
    "fatness": 0.11,
    "hairBg": {
        "id": "none"
    },
    "body": {
        "id": "body2",
        "color": "#88604a"
    },
    "jersey": {
        "id": "jersey3"
    },
    "ear": {
        "id": "ear2",
        "size": 1
    },
    "head": {
        "id": "head1",
        "shave": "rgba(0,0,0,0)"
    },
    "eyeLine": {
        "id": "none"
    },
    "smileLine": {
        "id": "line2",
        "size": 0.5
    },
    "miscLine": {
        "id": "none"
    },
    "facialHair": {
        "id": "goatee-thin-stache"
    },
    "eye": {
        "id": "eye16",
        "angle": -5
    },
    "eyebrow": {
        "id": "eyebrow18",
        "angle": 4
    },
    "hair": {
        "id": "short",
        "color": "#100d09",
        "flip": true
    },
    "mouth": {
        "id": "mouth4",
        "flip": true
    },
    "nose": {
        "id": "nose12",
        "flip": true,
        "size": 0.76
    },
    "glasses": {
        "id": "none"
    },
    "accessories": {
        "id": "none"
    }
}