{
    "fatness": -0.12,
    "hairBg": {
        "id": "none"
    },
    "body": {
        "id": "body5",
        "color": "#e2b5a7"
    },
    "jersey": {
        "id": "jersey2"
    },
    "ear": {
        "id": "ear2",
        "size": 1
    },
    "head": {
        "id": "head2",
        "shave": "rgba(0,0,0,0)"
    },
    "eyeLine": {
        "id": "line5"
    },
    "smileLine": {
        "id": "none",
        "size": 0.98
    },
    "miscLine": {
        "id": "freckles1"
    },
    "facialHair": {
        "id": "beard2"
    },
    "eye": {
        "id": "eye13",
        "angle": -7
    },
    "eyebrow": {
        "id": "eyebrow16",
        "angle": -1
    },
    "hair": {
        "id": "shortBangs",
        "color": "#311918",
        "flip": true
    },
    "mouth": {
        "id": "straight",
        "flip": true
    },
    "nose": {
        "id": "nose7",
        "flip": false,
        "size": 0.94
    },
    "glasses": {
        "id": "none"
    },
    "accessories": {
        "id": "none"
    }
}