{
    "fatness": 0.11,
    "hairBg": {
        "id": "none"
    },
    "body": {
        "id": "body4",
        "color": "#dfc2ae"
    },
    "jersey": {
        "id": "jersey3"
    },
    "ear": {
        "id": "ear1",
        "size": 1.11
    },
    "head": {
        "id": "head1",
        "shave": "rgba(0,0,0,0)"
    },
    "eyeLine": {
        "id": "line5"
    },
    "smileLine": {
        "id": "none",
        "size": 1.62
    },
    "miscLine": {
        "id": "none"
    },
    "facialHair": {
        "id": "chin-strapStache"
    },
    "eye": {
        "id": "eye13",
        "angle": -6
    },
    "eyebrow": {
        "id": "eyebrow7",
        "angle": -2
    },
    "hair": {
        "id": "messy",
        "color": "#673e25",
        "flip": true
    },
    "mouth": {
        "id": "mouth7",
        "flip": true
    },
    "nose": {
        "id": "nose7",
        "flip": true,
        "size": 1.06
    },
    "glasses": {
        "id": "none"
    },
    "accessories": {
        "id": "none"
    }
}