{
    "fatness": 0.28,
    "hairBg": {
        "id": "none"
    },
    "body": {
        "id": "body2",
        "color": "#ebc1aa"
    },
    "jersey": {
        "id": "jersey3"
    },
    "ear": {
        "id": "ear3",
        "size": 1.3
    },
    "head": {
        "id": "head2",
        "shave": "rgba(0,0,0,0)"
    },
    "eyeLine": {
        "id": "line5"
    },
    "smileLine": {
        "id": "none",
        "size": 0.5
    },
    "miscLine": {
        "id": "none"
    },
    "facialHair": {
        "id": "chin-strap"
    },
    "eye": {
        "id": "eye6",
        "angle": 0
    },
    "eyebrow": {
        "id": "eyebrow16",
        "angle": 4
    },
    "hair": {
        "id": "spike2",
        "color": "#32312d",
        "flip": false
    },
    "mouth": {
        "id": "straight",
        "flip": false
    },
    "nose": {
        "id": "nose7",
        "flip": false,
        "size": 1.08
    },
    "glasses": {
        "id": "none"
    },
    "accessories": {
        "id": "none"
    }
}