{
    "fatness": 0.08,
    "hairBg": {
        "id": "none"
    },
    "body": {
        "id": "body",
        "color": "#c39581"
    },
    "jersey": {
        "id": "jersey3"
    },
    "ear": {
        "id": "ear1",
        "size": 1
    },
    "head": {
        "id": "head6",
        "shave": "rgba(0,0,0,0)"
    },
    "eyeLine": {
        "id": "none"
    },
    "smileLine": {
        "id": "none",
        "size": 1.95
    },
    "miscLine": {
        "id": "forehead2"
    },
    "facialHair": {
        "id": "goatee4"
    },
    "eye": {
        "id": "eye7",
        "angle": -3
    },
    "eyebrow": {
        "id": "eyebrow13",
        "angle": 4
    },
    "hair": {
        "id": "blowoutFade",
        "color": "#100d09",
        "flip": false
    },
    "mouth": {
        "id": "smile",
        "flip": false
    },
    "nose": {
        "id": "nose5",
        "flip": false,
        "size": 0.96
    },
    "glasses": {
        "id": "none"
    },
    "accessories": {
        "id": "none"
    }
}